flowgym/__init__.py
flowgym/make.py
flowgym/py.typed
flowgym/registry.py
flowgym/types.py
flowgym/utils.py
flowgym/base_models/__init__.py
flowgym/base_models/base.py
flowgym/base_models/one_dim_gmm.py
flowgym/environments/__init__.py
flowgym/environments/base.py
flowgym/environments/endpoint.py
flowgym/environments/epsilon.py
flowgym/environments/score.py
flowgym/environments/velocity.py
flowgym/images/__init__.py
flowgym/images/base_models/cifar.py
flowgym/images/base_models/dit.py
flowgym/images/base_models/refl_data.json
flowgym/images/base_models/stable_diffusion.py
flowgym/images/rewards/__init__.py
flowgym/images/rewards/aesthetic.py
flowgym/images/rewards/compression.py
flowgym/molecules/__init__.py
flowgym/molecules/types.py
flowgym/molecules/base_models/flowmol_model.py
flowgym/molecules/base_models/qm9_dipole_moments.json
flowgym/molecules/rewards/qed.py
flowgym/molecules/rewards/utils.py
flowgym/molecules/rewards/validity.py
flowgym/molecules/rewards/xtb.py
flowgym/rewards/__init__.py
flowgym/rewards/base.py
flowgym/rewards/one_dim.py
flowgym/schedulers/__init__.py
flowgym/schedulers/base.py
flowgym/schedulers/noise_schedules.py
flowgym/schedulers/schedulers.py
flowgym-1.13.dist-info/METADATA
flowgym-1.13.dist-info/WHEEL
flowgym-1.13.dist-info/licenses/LICENSE
flowgym-1.13.dist-info/RECORD
