Metadata-Version: 2.4
Name: flowgym
Version: 1.13
Summary: Flow Gym
Project-URL: Homepage, https://github.com/cristianpjensen/flowgym
Project-URL: Issues, https://github.com/cristianpjensen/flowgym/issues
Author: Cristian Perez Jensen
License: MIT License
License-File: LICENSE
Requires-Python: <3.12,>=3.8
Requires-Dist: datasets==2.11.0
Requires-Dist: dgl==2.4
Requires-Dist: diffusers==0.33.1
Requires-Dist: meeko==0.6.1
Requires-Dist: numpy<2,>=1.24
Requires-Dist: open-clip-torch<3,>=2.26
Requires-Dist: pandas<3,>=2
Requires-Dist: polars<2,>=1.34.0
Requires-Dist: prody<3,>=2.4
Requires-Dist: pyarrow==11.0.0
Requires-Dist: pydantic<3,>=1.10
Requires-Dist: pyyaml<7,>=6
Requires-Dist: rdkit-stubs<0.9,>=0.6
Requires-Dist: rdkit<2025,>=2023.9.4
Requires-Dist: torch==2.3.1
Requires-Dist: torchdata<0.9,>=0.7
Requires-Dist: torchvision==0.18.1
Requires-Dist: tqdm<5,>=4.66
Requires-Dist: transformers>=4.36
Requires-Dist: typing-extensions<5,>=4.9
